hatchet/__init__.py
hatchet/node.py
hatchet/graphframe.py
hatchet/version.py
hatchet/frame.py
hatchet/graph.py
hatchet/query/__init__.py
hatchet/query/string_dialect.py
hatchet/query/compound.py
hatchet/query/errors.py
hatchet/query/engine.py
hatchet/query/compat.py
hatchet/query/query.py
hatchet/query/object_dialect.py
hatchet/cython_modules/graphframe_modules.pyx
hatchet/cython_modules/reader_modules.pyx
hatchet/cython_modules/libs/__init__.py
hatchet/cython_modules/libs/reader_modules.cpython-37m-x86_64-linux-gnu.so
hatchet/cython_modules/libs/graphframe_modules.cpython-37m-x86_64-linux-gnu.so
hatchet/external/__init__.py
hatchet/external/console.py
hatchet/external/roundtrip/__init__.py
hatchet/external/roundtrip/setup.py
hatchet/external/roundtrip/pyproject.toml
hatchet/external/roundtrip/package.json
hatchet/external/roundtrip/NOTICE
hatchet/external/roundtrip/requirements.txt
hatchet/external/roundtrip/LICENSE
hatchet/external/roundtrip/README.md
hatchet/external/roundtrip/roundtrip/__init__.py
hatchet/external/roundtrip/roundtrip/manager.py
hatchet/external/roundtrip/roundtrip/version.py
hatchet/external/roundtrip/roundtrip/roundtrip.js
hatchet/external/roundtrip/roundtrip/tests/rt_test.py
hatchet/external/roundtrip/roundtrip/tests/data/test.html
hatchet/external/roundtrip/roundtrip/tests/data/test.js
hatchet/tests/timemory_func.py
hatchet/tests/caliper.py
hatchet/tests/callgrind.py
hatchet/tests/executable.py
hatchet/tests/node.py
hatchet/tests/timemory_test.py
hatchet/tests/multi_rank.py
hatchet/tests/json_test.py
hatchet/tests/tau.py
hatchet/tests/dataframe_ops.py
hatchet/tests/hpctoolkit.py
hatchet/tests/query_compat.py
hatchet/tests/hpctoolkit_latest.py
hatchet/tests/pyinstrument.py
hatchet/tests/graph_literal.py
hatchet/tests/graphframe.py
hatchet/tests/conftest.py
hatchet/tests/spotdb_test.py
hatchet/tests/cprofile.py
hatchet/tests/profiler.py
hatchet/tests/frame.py
hatchet/tests/graph_ops.py
llnl_hatchet-2025.1.1.dist-info/top_level.txt
llnl_hatchet-2025.1.1.dist-info/WHEEL
llnl_hatchet-2025.1.1.dist-info/RECORD
llnl_hatchet-2025.1.1.dist-info/METADATA
llnl_hatchet-2025.1.1.dist-info/NOTICE
llnl_hatchet-2025.1.1.dist-info/LICENSE
