Metadata-Version: 2.1
Name: llnl-hatchet
Version: 2025.1.1
Summary: A Python library for analyzing hierarchical performance data
Home-page: https://github.com/llnl/hatchet
Author: Stephanie Brink
Author-email: brink2@llnl.gov
License: MIT
Project-URL: Source Code, https://github.com/llnl/hatchet
Project-URL: Documentation, https://llnl-hatchet.readthedocs.io/en/latest/
Classifier: Development Status :: 5 - Production/Stable
Classifier: License :: OSI Approved :: MIT License
Requires-Python: >=3.5
License-File: LICENSE
License-File: NOTICE
Requires-Dist: pydot
Requires-Dist: PyYAML
Requires-Dist: matplotlib
Requires-Dist: numpy
Requires-Dist: pandas
Requires-Dist: multiprocess
Requires-Dist: caliper-reader
Requires-Dist: textX <3.0.0 ; python_version < "3.6"
Requires-Dist: textX >=3.0.0 ; python_version >= "3.6"
